tinybird/__init__.py
tinybird/beam.py
tinybird_beam-1.0.0b1.dist-info/LICENSE
tinybird_beam-1.0.0b1.dist-info/METADATA
tinybird_beam-1.0.0b1.dist-info/WHEEL
tinybird_beam-1.0.0b1.dist-info/top_level.txt
tinybird_beam-1.0.0b1.dist-info/RECORD
