Metadata-Version: 2.1
Name: tinybird-beam
Version: 1.0.0b1
Summary: An Apache Beam Sink Library for Tinybird.
Home-page: UNKNOWN
Author: Tinybird
Author-email: support@tinybird.co
License: UNKNOWN
Platform: UNKNOWN
Requires-Dist: requests (==2.25.1)
Requires-Dist: apache-beam[gcp] (==2.27.0)
